redturtle.voltoplugin.editablefooter-2.0.0-py3.11-nspkg.pth
redturtle/voltoplugin/editablefooter/__init__.py
redturtle/voltoplugin/editablefooter/configure.zcml
redturtle/voltoplugin/editablefooter/interfaces.py
redturtle/voltoplugin/editablefooter/permissions.zcml
redturtle/voltoplugin/editablefooter/setuphandlers.py
redturtle/voltoplugin/editablefooter/testing.py
redturtle/voltoplugin/editablefooter/browser/__init__.py
redturtle/voltoplugin/editablefooter/browser/configure.zcml
redturtle/voltoplugin/editablefooter/browser/controlpanel.py
redturtle/voltoplugin/editablefooter/locales/README.rst
redturtle/voltoplugin/editablefooter/locales/__init__.py
redturtle/voltoplugin/editablefooter/locales/redturtle.voltoplugin.editablefooter.pot
redturtle/voltoplugin/editablefooter/locales/update.py
redturtle/voltoplugin/editablefooter/locales/update.sh
redturtle/voltoplugin/editablefooter/locales/en/LC_MESSAGES/redturtle.voltoplugin.editablefooter.po
redturtle/voltoplugin/editablefooter/locales/it/LC_MESSAGES/redturtle.voltoplugin.editablefooter.po
redturtle/voltoplugin/editablefooter/profiles/default/browserlayer.xml
redturtle/voltoplugin/editablefooter/profiles/default/catalog.xml
redturtle/voltoplugin/editablefooter/profiles/default/controlpanel.xml
redturtle/voltoplugin/editablefooter/profiles/default/metadata.xml
redturtle/voltoplugin/editablefooter/profiles/default/registry.xml
redturtle/voltoplugin/editablefooter/profiles/default/rolemap.xml
redturtle/voltoplugin/editablefooter/profiles/uninstall/browserlayer.xml
redturtle/voltoplugin/editablefooter/profiles/uninstall/controlpanel.xml
redturtle/voltoplugin/editablefooter/profiles/uninstall/registry.xml
redturtle/voltoplugin/editablefooter/restapi/__init__.py
redturtle/voltoplugin/editablefooter/restapi/configure.zcml
redturtle/voltoplugin/editablefooter/restapi/controlpanel.py
redturtle/voltoplugin/editablefooter/restapi/deserializer.py
redturtle/voltoplugin/editablefooter/restapi/get.py
redturtle_voltoplugin_editablefooter-2.0.0.dist-info/LICENSE.GPL
redturtle_voltoplugin_editablefooter-2.0.0.dist-info/LICENSE.rst
redturtle_voltoplugin_editablefooter-2.0.0.dist-info/METADATA
redturtle_voltoplugin_editablefooter-2.0.0.dist-info/WHEEL
redturtle_voltoplugin_editablefooter-2.0.0.dist-info/entry_points.txt
redturtle_voltoplugin_editablefooter-2.0.0.dist-info/namespace_packages.txt
redturtle_voltoplugin_editablefooter-2.0.0.dist-info/top_level.txt
redturtle_voltoplugin_editablefooter-2.0.0.dist-info/RECORD
